<annotation>
	<folder>my-project-name</folder>
	<filename>126.jpg</filename>
	<path>/my-project-name/23 .jpg</path>
	<source>
		<database>Unspecified</database>
	</source>
	<size>
		<width>1280</width>
		<height>720</height>
		<depth>3</depth>
	</size>
	<object>
		<name>cam_nguoc_chieu</name>
		<pose>Unspecified</pose>
		<truncated>0</truncated>
		<difficult>0</difficult>
		<bndbox>
			<xmin>530</xmin>
			<ymin>343</ymin>
			<xmax>542</xmax>
			<ymax>355</ymax>
		</bndbox>
	</object>
	<object>
		<name>huong_phai_di_vong</name>
		<pose>Unspecified</pose>
		<truncated>0</truncated>
		<difficult>0</difficult>
		<bndbox>
			<xmin>530</xmin>
			<ymin>355</ymin>
			<xmax>542</xmax>
			<ymax>367</ymax>
		</bndbox>
	</object>
</annotation>